seventeenlands/__init__.py
seventeenlands/api_client.py
seventeenlands/logging_utils.py
seventeenlands/mtga_follower.py
seventeenlands/retry_utils.py
seventeenlands-0.1.43.dist-info/licenses/LICENSE
seventeenlands-0.1.43.dist-info/METADATA
seventeenlands-0.1.43.dist-info/WHEEL
seventeenlands-0.1.43.dist-info/entry_points.txt
seventeenlands-0.1.43.dist-info/top_level.txt
seventeenlands-0.1.43.dist-info/RECORD
