Metadata-Version: 2.4
Name: seventeenlands
Version: 0.1.43
Summary: Utility to upload MTG Arena data to 17Lands.com
Home-page: https://github.com/rconroy293/mtga-log-client
Author: Robert Conroy
Author-email: support@17lands.com
Classifier: Programming Language :: Python :: 3
Classifier: Operating System :: OS Independent
Requires-Python: >=3.6
License-File: LICENSE
Requires-Dist: requests
Requires-Dist: python-dateutil
Dynamic: author
Dynamic: author-email
Dynamic: classifier
Dynamic: description
Dynamic: description-content-type
Dynamic: home-page
Dynamic: license-file
Dynamic: requires-dist
Dynamic: requires-python
Dynamic: summary
